TCLIService/TCLIService.py
TCLIService/__init__.py
TCLIService/constants.py
TCLIService/ttypes.py
pytimbr_sqla/__init__.py
pytimbr_sqla/common.py
pytimbr_sqla/exc.py
pytimbr_sqla/hive.py
pytimbr_sqla/sasl_compat.py
pytimbr_sqla/sqlalchemy_timbr.py
pytimbr_sqla-2.1.0.dist-info/licenses/LICENSE
pytimbr_sqla-2.1.0.dist-info/licenses/licenses/LICENSE-Apache-2.0
pytimbr_sqla-2.1.0.dist-info/licenses/licenses/LICENSE-GPL-2.0-only
pytimbr_sqla-2.1.0.dist-info/licenses/licenses/LICENSE-GPL-3.0-only
pytimbr_sqla-2.1.0.dist-info/licenses/licenses/LICENSE-GPL-3.0-or-later
pytimbr_sqla-2.1.0.dist-info/licenses/licenses/LICENSE-LGPL-3.0-only
pytimbr_sqla-2.1.0.dist-info/licenses/licenses/LICENSE-MIT
thrift/__init__.py
thrift/transport/THttpClient.py
thrift/transport/__init__.py
pytimbr_sqla-2.1.0.dist-info/METADATA
pytimbr_sqla-2.1.0.dist-info/WHEEL
pytimbr_sqla-2.1.0.dist-info/entry_points.txt
pytimbr_sqla-2.1.0.dist-info/top_level.txt
pytimbr_sqla-2.1.0.dist-info/RECORD
