Metadata-Version: 2.4
Name: pytimbr_sqla
Version: 2.1.0
Summary: Timbr Python SQLAlchemy connector
Author-email: timbr <contact@timbr.ai>
Maintainer-email: timbr <contact@timbr.ai>
Project-URL: Homepage, https://github.com/WPSemantix/timbr_python_SQLAlchemy
Project-URL: Download, https://github.com/WPSemantix/timbr_python_SQLAlchemy/releases
Project-URL: Bug Tracker, https://github.com/WPSemantix/timbr_python_SQLAlchemy/issues
Project-URL: Repository, https://github.com/WPSemantix/timbr_python_SQLAlchemy
Project-URL: Documentation, https://github.com/WPSemantix/timbr_python_SQLAlchemy#readme
Keywords: timbr,timbr-python,timbr-connector,python-connector,PyTimbr,pytimbr,py-timbr,Py-Timbr,pytimbr_sqla,pytimbr_Sqla,PyTimbr_Sqla,pytimbr_SQla,PyTimbr_SQla,pytimbr_SQLa,PyTimbr_SQLa,pytimbr_SQlA,PyTimbr_SQLA,pytimbrsqlalchemy,PyTimbrSqlalchemy,PyTimbrSQlalchemy,PyTimbrSQLalchemy,PyTimbrSQLAlchemy,Py-TimbrSQLAlchemy,py-timbrsqlalchemy,Py-Timbr-SQLAlchemy,py-timbr-sqlalchemy
Classifier: Development Status :: 5 - Production/Stable
Classifier: Intended Audience :: Developers
Classifier: Topic :: Software Development :: Build Tools
Classifier: Programming Language :: Python :: 3
Classifier: Programming Language :: Python :: 3.9
Classifier: Programming Language :: Python :: 3.10
Classifier: Programming Language :: Python :: 3.11
Classifier: Programming Language :: Python :: 3.12
Requires-Python: >=3.9
License-File: LICENSE
License-File: licenses/LICENSE-Apache-2.0
License-File: licenses/LICENSE-GPL-2.0-only
License-File: licenses/LICENSE-GPL-3.0-only
License-File: licenses/LICENSE-GPL-3.0-or-later
License-File: licenses/LICENSE-LGPL-3.0-only
License-File: licenses/LICENSE-MIT
Requires-Dist: future>=0.18.3
Requires-Dist: python-dateutil>=2.8.2
Requires-Dist: ldap3
Requires-Dist: thrift>=0.16.0
Requires-Dist: thrift_sasl>=0.4.3
Requires-Dist: pure-sasl>=0.6.2
Requires-Dist: sqlalchemy<2.0.0,>=1.4.36
Requires-Dist: requests_kerberos>=0.12.0
Requires-Dist: pyhive>=0.7.0
Dynamic: license-file
